<?xml version="1.0" encoding="UTF-8"?>
<molecule id="aspirin" convention="cml:PML-cartesian" xmlns:f="http://www.xml-cml.org/mols/geom" xmlns="http://www.xml-cml.org/schema">
  <atomArray>
    <atom elementType="C" hydrogenCount="3" id="acet_1_a1" x3="0.0" y3="0.0" z3="0.0"> </atom>
    <atom elementType="C" hydrogenCount="0" id="acet_1_a2" x3="1.52" y3="0.0" z3="0.0"> </atom>
    <atom elementType="O" hydrogenCount="0" id="acet_1_a3" x3="1.52" y3="0.0" z3="0.5"> </atom>
    <atom elementType="O" hydrogenCount="0" id="acet_1_a4" x3="2.0217151293634203" y3="1.3070125970960824" z3="0.0"> </atom>
    <atom elementType="C" hydrogenCount="1" id="ophen_2_a1" x3="5.652120943183128" y3="0.6632318681331355" z3="8.855803243352971E-16"> </atom>
    <atom elementType="C" hydrogenCount="1" id="ophen_2_a2" x3="6.150252393051096" y3="1.9609086609642457" z3="7.381603661525351E-16"> </atom>
    <atom elementType="C" hydrogenCount="1" id="ophen_2_a3" x3="5.275497049491822" y3="3.0411415473894357" z3="2.95900491604249E-16"> </atom>
    <atom elementType="C" hydrogenCount="1" id="ophen_2_a4" x3="3.9026102560645803" y3="2.8236976409835153" z3="1.0605752387248717E-18"> </atom>
    <atom elementType="C" hydrogenCount="0" id="ophen_2_a5" x3="3.404478806196613" y3="1.5260208481524054" z3="1.4848053342148696E-16"> </atom>
    <atom elementType="C" hydrogenCount="0" id="ophen_2_a6" x3="4.2792341497558875" y3="0.44578796172721624" z3="5.90740407969773E-16"> </atom>
    <atom elementType="O" hydrogenCount="1" id="coxy_3_a1" x3="1.52" y3="0.0" z3="1.5"> </atom>
    <atom elementType="C" hydrogenCount="0" id="coxy_3_a2" x3="1.52" y3="0.0" z3="2.0"> </atom>
    <atom elementType="O" hydrogenCount="0" id="coxy_3_a3" x3="1.52" y3="0.0" z3="3.0"> </atom>
  </atomArray>
  <bondArray>
    <bond order="1" id="acet_1_a1_acet_1_a2" atomRefs2="acet_1_a1 acet_1_a2"> </bond>
    <bond order="2" id="acet_1_a2_acet_1_a3" atomRefs2="acet_1_a2 acet_1_a3"> </bond>
    <bond order="1" id="acet_1_a2_acet_1_a4" atomRefs2="acet_1_a2 acet_1_a4"> </bond>
    <bond order="A" id="ophen_2_a1_ophen_2_a2" atomRefs2="ophen_2_a1 ophen_2_a2"> </bond>
    <bond order="A" id="ophen_2_a2_ophen_2_a3" atomRefs2="ophen_2_a2 ophen_2_a3"> </bond>
    <bond order="A" id="ophen_2_a3_ophen_2_a4" atomRefs2="ophen_2_a3 ophen_2_a4"> </bond>
    <bond order="A" id="ophen_2_a4_ophen_2_a5" atomRefs2="ophen_2_a4 ophen_2_a5"> </bond>
    <bond order="A" id="ophen_2_a5_ophen_2_a6" atomRefs2="ophen_2_a5 ophen_2_a6"> </bond>
    <bond order="A" id="ophen_2_a1_ophen_2_a6" atomRefs2="ophen_2_a1 ophen_2_a6"> </bond>
    <bond order="1" id="coxy_3_a1_coxy_3_a2" atomRefs2="coxy_3_a1 coxy_3_a2"> </bond>
    <bond order="2" id="coxy_3_a2_coxy_3_a3" atomRefs2="coxy_3_a2 coxy_3_a3"> </bond>
    <bond atomRefs2="acet_1_a4 ophen_2_a5" id="f:acet_1_r1_f:ophen_2_r1" order="1"/>
    <bond atomRefs2="ophen_2_a6 coxy_3_a2" id="f:ophen_2_r2_f:coxy_3_r1" order="1"/>
  </bondArray>
  <torsion atomRefs4="acet_1_a1 acet_1_a2 acet_1_a4 ophen_2_a5">180</torsion>
  <angle atomRefs3="acet_1_a2 acet_1_a4 ophen_2_a5">120</angle>
  <torsion atomRefs4="acet_1_a1 acet_1_a4 acet_1_a2 acet_1_a3">180</torsion>
  <angle atomRefs3="acet_1_a1 acet_1_a2 acet_1_a4">111</angle>
  <length atomRefs2="acet_1_a2 acet_1_a4">1.40</length>
  <angle atomRefs3="acet_1_a1 acet_1_a2 acet_1_a3">111</angle>
  <length atomRefs2="acet_1_a2 acet_1_a3">1.25</length>
  <length atomRefs2="acet_1_a1 acet_1_a2">1.52</length>
  <name>acet_1</name>
  <name>ophen_2</name>
  <torsion atomRefs4="ophen_2_a4 ophen_2_a5 ophen_2_r6 coxy_3_a2"> 180</torsion>
  <angle atomRefs3="ophen_2_a5 ophen_2_a6 coxy_3_a2"> 120</angle>
  <torsion atomRefs4="ophen_2_a3 ophen_2_a4 ophen_2_a5 acet_1_a4"> 180</torsion>
  <angle atomRefs3="ophen_2_a4 ophen_2_a5 acet_1_a4"> 120</angle>
  <torsion atomRefs4="ophen_2_a3 ophen_2_a4 ophen_2_a5 ophen_2_a6"> 0</torsion>
  <angle atomRefs3="ophen_2_a4 ophen_2_a5 ophen_2_a6"> 120</angle>
  <length atomRefs2="ophen_2_a5 ophen_2_a6"> 1.39</length>
  <torsion atomRefs4="ophen_2_a2 ophen_2_a3 ophen_2_a4 ophen_2_a5"> 0</torsion>
  <angle atomRefs3="ophen_2_a3 ophen_2_a4 ophen_2_a5"> 120</angle>
  <length atomRefs2="ophen_2_a4 ophen_2_a5"> 1.39</length>
  <torsion atomRefs4="ophen_2_a1 ophen_2_a2 ophen_2_a3 ophen_2_a4"> 0</torsion>
  <angle atomRefs3="ophen_2_a2 ophen_2_a3 ophen_2_a4"> 120</angle>
  <length atomRefs2="ophen_2_a3 ophen_2_a4"> 1.39</length>
  <angle atomRefs3="ophen_2_a1 ophen_2_a2 ophen_2_a3"> 120</angle>
  <length atomRefs2="ophen_2_a2 ophen_2_a3"> 1.39</length>
  <length atomRefs2="ophen_2_a1 ophen_2_a2"> 1.39</length>
  <name>coxy_3</name>
  <torsion atomRefs4="coxy_3_a1 coxy_3_a3 coxy_3_a2 ophen_2_a6"> 120</torsion>
  <angle atomRefs3="coxy_3_a1 coxy_3_a2 ophen_2_a6"> 120</angle>
  <angle atomRefs3="coxy_3_a1 coxy_3_a2 coxy_3_a3"> 120</angle>
  <length atomRefs2="coxy_3_a2 coxy_3_a3"> 1.25</length>
  <length atomRefs2="coxy_3_a1 coxy_3_a2"> 1.32</length>
  <length atomRefs2="acet_1_a4 ophen_2_a5">1.4</length>
  <torsion atomRefs4="acet_1_a2 acet_1_a4 ophen_2_a5 ophen_2_a4">180.0</torsion>
  <length atomRefs2="ophen_2_a6 coxy_3_a2">1.4</length>
  <torsion atomRefs4="ophen_2_a5 ophen_2_a6 coxy_3_a2 coxy_3_a1">180.0</torsion>
</molecule>
